{"total":95,"pageSize":12,"pageCount":8,"data":[{"title":"第五章 数组与广义表","uid":"bf6cf56a339e6629e90121a02e6ba708","slug":"专业基础/数据结构/第五章 数组与广义表","date":"2020-08-09T02:53:37.000Z","updated":"2021-09-26T13:34:19.056Z","comments":true,"path":"api/articles/专业基础/数据结构/第五章 数组与广义表.json","cover":[],"text":" 数组与广义表 数组 数组的定义 数组的逻辑结构 一维数组： 多维数组： 数组的抽象数据类型： 数组的基本操作： 数组运算的关键在于找到对应元素的下标。 数组的存储结构 顺序存储结构：数组中的所有元素存储在一块地址连续的内存单元中,使用的是顺序存储结构。（不要把数组与顺序存储结构...","link":"","photos":[],"count_time":{"symbolsCount":"6.9k","symbolsTime":"6 mins."},"categories":[{"name":"专业基础","slug":"专业基础","count":24,"path":"api/categories/专业基础.json"},{"name":"数据结构","slug":"专业基础/数据结构","count":8,"path":"api/categories/专业基础/数据结构.json"}],"tags":[{"name":"数据结构","slug":"数据结构","count":14,"path":"api/tags/数据结构.json"}],"author":{"name":"ZestJourney","slug":"blog-author","avatar":"https://zjpicture.oss-cn-beijing.aliyuncs.com/img/20210822091020.jpg","link":"/","description":"吾好梦中读书~","socials":{"github":"","twitter":"","stackoverflow":"","wechat":"","qq":"","weibo":"","zhihu":"","csdn":"","juejin":"","customs":{"QQ":{"icon":"/svg/qq.svg","link":"https://gitee.com/zhangjie0524/picgo/raw/master/20210822092319.jpg"},"WeiXin":{"icon":"/svg/weixin.svg","link":"https://gitee.com/zhangjie0524/picgo/raw/master/20210822092515.png"},"Github":{"icon":"/svg/github.svg","link":"https://github.com/zestaken"}}}}},{"title":"第四章 串","uid":"92e7d7cd5512fd8cb0f937659bf677c5","slug":"专业基础/数据结构/第四章 串","date":"2020-08-03T02:53:37.000Z","updated":"2021-09-26T13:34:19.056Z","comments":true,"path":"api/articles/专业基础/数据结构/第四章 串.json","cover":[],"text":" 第四章 串 串的定义 串： 串也是一种线性表 串相等： 长度相等且对应位置相等。 所有的空串相等。 子串： 类似子集的定义。 基本运算： 串的存储结构 顺序串：用顺序存储结构（数组）存储，且为存储结构为定长。 堆串：用顺序存储结构存储，但存储结构的长度是根据串的长度来动态分配的...","link":"","photos":[],"count_time":{"symbolsCount":"4.4k","symbolsTime":"4 mins."},"categories":[{"name":"专业基础","slug":"专业基础","count":24,"path":"api/categories/专业基础.json"},{"name":"数据结构","slug":"专业基础/数据结构","count":8,"path":"api/categories/专业基础/数据结构.json"}],"tags":[{"name":"数据结构","slug":"数据结构","count":14,"path":"api/tags/数据结构.json"}],"author":{"name":"ZestJourney","slug":"blog-author","avatar":"https://zjpicture.oss-cn-beijing.aliyuncs.com/img/20210822091020.jpg","link":"/","description":"吾好梦中读书~","socials":{"github":"","twitter":"","stackoverflow":"","wechat":"","qq":"","weibo":"","zhihu":"","csdn":"","juejin":"","customs":{"QQ":{"icon":"/svg/qq.svg","link":"https://gitee.com/zhangjie0524/picgo/raw/master/20210822092319.jpg"},"WeiXin":{"icon":"/svg/weixin.svg","link":"https://gitee.com/zhangjie0524/picgo/raw/master/20210822092515.png"},"Github":{"icon":"/svg/github.svg","link":"https://github.com/zestaken"}}}}},{"title":"Make及Makefile","uid":"498734381a67107f010f02554f6e2a67","slug":"技术笔记/Linux/Make及Makefile","date":"2020-07-31T14:28:31.000Z","updated":"2021-09-26T13:42:00.073Z","comments":true,"path":"api/articles/技术笔记/Linux/Make及Makefile.json","cover":[],"text":" Make及Makefile Make 代码变成可执行文件，叫做编译（compile）；先编译这个，还是先编译那个（即编译的安排），叫做构建（build）。 Make是最常用的构建工具，诞生于1977年，主要用于C语言的项目。但是实际上 ，任何只要某个文件有变化，就要重新构建的项...","link":"","photos":[],"count_time":{"symbolsCount":"6.2k","symbolsTime":"6 mins."},"categories":[{"name":"技术笔记","slug":"技术笔记","count":67,"path":"api/categories/技术笔记.json"},{"name":"Linux","slug":"技术笔记/Linux","count":6,"path":"api/categories/技术笔记/Linux.json"}],"tags":[{"name":"C","slug":"C","count":7,"path":"api/tags/C.json"},{"name":"Linux","slug":"Linux","count":6,"path":"api/tags/Linux.json"},{"name":"MakeFile","slug":"MakeFile","count":1,"path":"api/tags/MakeFile.json"}],"author":{"name":"ZestJourney","slug":"blog-author","avatar":"https://zjpicture.oss-cn-beijing.aliyuncs.com/img/20210822091020.jpg","link":"/","description":"吾好梦中读书~","socials":{"github":"","twitter":"","stackoverflow":"","wechat":"","qq":"","weibo":"","zhihu":"","csdn":"","juejin":"","customs":{"QQ":{"icon":"/svg/qq.svg","link":"https://gitee.com/zhangjie0524/picgo/raw/master/20210822092319.jpg"},"WeiXin":{"icon":"/svg/weixin.svg","link":"https://gitee.com/zhangjie0524/picgo/raw/master/20210822092515.png"},"Github":{"icon":"/svg/github.svg","link":"https://github.com/zestaken"}}}}},{"title":"第三章 栈与队列","uid":"80ca1b21183ee8dc9dbbd142f336c853","slug":"专业基础/数据结构/第三章 栈与队列","date":"2020-07-31T09:25:37.000Z","updated":"2021-09-26T13:34:19.067Z","comments":true,"path":"api/articles/专业基础/数据结构/第三章 栈与队列.json","cover":[],"text":" 第三章 限定性线性表-栈与队列 栈 定义 栈与队列都是特殊的线性表，是操作受限的线性表，称为限定性线性表。 特点：先进后出（FILO:first in last out）或后进先出（LIFO:last in first out） 线性表可以在任意位置插入、删除，而栈只允许在栈顶...","link":"","photos":[],"count_time":{"symbolsCount":"5.7k","symbolsTime":"5 mins."},"categories":[{"name":"专业基础","slug":"专业基础","count":24,"path":"api/categories/专业基础.json"},{"name":"数据结构","slug":"专业基础/数据结构","count":8,"path":"api/categories/专业基础/数据结构.json"}],"tags":[{"name":"数据结构","slug":"数据结构","count":14,"path":"api/tags/数据结构.json"}],"author":{"name":"ZestJourney","slug":"blog-author","avatar":"https://zjpicture.oss-cn-beijing.aliyuncs.com/img/20210822091020.jpg","link":"/","description":"吾好梦中读书~","socials":{"github":"","twitter":"","stackoverflow":"","wechat":"","qq":"","weibo":"","zhihu":"","csdn":"","juejin":"","customs":{"QQ":{"icon":"/svg/qq.svg","link":"https://gitee.com/zhangjie0524/picgo/raw/master/20210822092319.jpg"},"WeiXin":{"icon":"/svg/weixin.svg","link":"https://gitee.com/zhangjie0524/picgo/raw/master/20210822092515.png"},"Github":{"icon":"/svg/github.svg","link":"https://github.com/zestaken"}}}}},{"title":"GCC基础","uid":"96dcb211a687b174b8ad0d4517b9e4a1","slug":"技术笔记/杂技术/GCC基础","date":"2020-07-28T02:01:51.000Z","updated":"2021-10-27T23:56:57.044Z","comments":true,"path":"api/articles/技术笔记/杂技术/GCC基础.json","cover":[],"text":" GCC基础 GCC简介 早期 GCC 的全拼为 GNU C Compiler，即 GUN 计划诞生的 C 语言编译器，显然最初 GCC 的定位确实只用于编译 C 语言。但经过这些年不断的迭代，GCC 的功能得到了很大的扩展，它不仅可以用来编译 C 语言程序，还可以处理 C++、...","link":"","photos":[],"count_time":{"symbolsCount":"9.1k","symbolsTime":"8 mins."},"categories":[{"name":"技术笔记","slug":"技术笔记","count":67,"path":"api/categories/技术笔记.json"},{"name":"杂技术","slug":"技术笔记/杂技术","count":8,"path":"api/categories/技术笔记/杂技术.json"}],"tags":[{"name":"C","slug":"C","count":7,"path":"api/tags/C.json"},{"name":"GCC","slug":"GCC","count":1,"path":"api/tags/GCC.json"}],"author":{"name":"ZestJourney","slug":"blog-author","avatar":"https://zjpicture.oss-cn-beijing.aliyuncs.com/img/20210822091020.jpg","link":"/","description":"吾好梦中读书~","socials":{"github":"","twitter":"","stackoverflow":"","wechat":"","qq":"","weibo":"","zhihu":"","csdn":"","juejin":"","customs":{"QQ":{"icon":"/svg/qq.svg","link":"https://gitee.com/zhangjie0524/picgo/raw/master/20210822092319.jpg"},"WeiXin":{"icon":"/svg/weixin.svg","link":"https://gitee.com/zhangjie0524/picgo/raw/master/20210822092515.png"},"Github":{"icon":"/svg/github.svg","link":"https://github.com/zestaken"}}}}},{"title":"vim","uid":"38f753080d8e70e9b431bdcf3f65115d","slug":"技术笔记/杂技术/vim","date":"2020-07-16T09:25:37.000Z","updated":"2021-09-26T13:39:56.530Z","comments":true,"path":"api/articles/技术笔记/杂技术/vim.json","cover":null,"text":" vim vim中的六种基本模式 几乎所有的编辑器都会有插入和执行命令两种模式，并且大多数的编辑器使用了与Vim截然不同的方式：命令目录（鼠标或者键盘驱动），组合键（通常通过control键（CTRL）和alt键（ALT）组成）或者鼠标输入。Vim和vi一样，仅仅通过键盘来在这些...","link":"","photos":[],"count_time":{"symbolsCount":"7.1k","symbolsTime":"6 mins."},"categories":[{"name":"技术笔记","slug":"技术笔记","count":67,"path":"api/categories/技术笔记.json"},{"name":"杂技术","slug":"技术笔记/杂技术","count":8,"path":"api/categories/技术笔记/杂技术.json"}],"tags":[{"name":"杂技术","slug":"杂技术","count":5,"path":"api/tags/杂技术.json"},{"name":"VIM","slug":"VIM","count":1,"path":"api/tags/VIM.json"}],"author":{"name":"ZestJourney","slug":"blog-author","avatar":"https://zjpicture.oss-cn-beijing.aliyuncs.com/img/20210822091020.jpg","link":"/","description":"吾好梦中读书~","socials":{"github":"","twitter":"","stackoverflow":"","wechat":"","qq":"","weibo":"","zhihu":"","csdn":"","juejin":"","customs":{"QQ":{"icon":"/svg/qq.svg","link":"https://gitee.com/zhangjie0524/picgo/raw/master/20210822092319.jpg"},"WeiXin":{"icon":"/svg/weixin.svg","link":"https://gitee.com/zhangjie0524/picgo/raw/master/20210822092515.png"},"Github":{"icon":"/svg/github.svg","link":"https://github.com/zestaken"}}}}},{"title":"第二章 线性表","uid":"8f934180a8825122f746c6e33ad53475","slug":"专业基础/数据结构/第二章 线性表","date":"2020-07-15T09:25:37.000Z","updated":"2021-09-26T13:34:19.056Z","comments":true,"path":"api/articles/专业基础/数据结构/第二章 线性表.json","cover":[],"text":" 第二章 线性表 线性表的定义 线性表是一个具有相同特性的数据元素的有限序列。 特性： 相同特性：所有元素属于同一数据类型。 有限：数据元素个数是有限的。 序列：数据元素由逻辑序号唯一确定。一个线性表中可以有相同值的元素。 结构：除第一个元素无前驱、最后一个元素无后继外，其余每个...","link":"","photos":[],"count_time":{"symbolsCount":"4.7k","symbolsTime":"4 mins."},"categories":[{"name":"专业基础","slug":"专业基础","count":24,"path":"api/categories/专业基础.json"},{"name":"数据结构","slug":"专业基础/数据结构","count":8,"path":"api/categories/专业基础/数据结构.json"}],"tags":[{"name":"数据结构","slug":"数据结构","count":14,"path":"api/tags/数据结构.json"}],"author":{"name":"ZestJourney","slug":"blog-author","avatar":"https://zjpicture.oss-cn-beijing.aliyuncs.com/img/20210822091020.jpg","link":"/","description":"吾好梦中读书~","socials":{"github":"","twitter":"","stackoverflow":"","wechat":"","qq":"","weibo":"","zhihu":"","csdn":"","juejin":"","customs":{"QQ":{"icon":"/svg/qq.svg","link":"https://gitee.com/zhangjie0524/picgo/raw/master/20210822092319.jpg"},"WeiXin":{"icon":"/svg/weixin.svg","link":"https://gitee.com/zhangjie0524/picgo/raw/master/20210822092515.png"},"Github":{"icon":"/svg/github.svg","link":"https://github.com/zestaken"}}}}},{"title":"第九章 内排序","uid":"bbb6deffd96f9a784d01082f99a2699f","slug":"专业基础/数据结构/第九章 内排序","date":"2020-06-28T09:25:37.000Z","updated":"2021-09-26T13:34:19.056Z","comments":true,"path":"api/articles/专业基础/数据结构/第九章 内排序.json","cover":[],"text":" 第九章 内排序 9.1 排序的概念 排序的定义 所谓排序，是整理表中的记录，使之按关键字递增（或递减）有序排列。 内排序与外排序 在排序过程中，若整个表都是放在内存中处理，排序时不涉及数据的内、外存交换，则称之为内排序；反之，若排序过程中要进行数据的内、外存交换，则称之为外排序...","link":"","photos":[],"count_time":{"symbolsCount":"2k","symbolsTime":"2 mins."},"categories":[{"name":"专业基础","slug":"专业基础","count":24,"path":"api/categories/专业基础.json"},{"name":"数据结构","slug":"专业基础/数据结构","count":8,"path":"api/categories/专业基础/数据结构.json"}],"tags":[{"name":"数据结构","slug":"数据结构","count":14,"path":"api/tags/数据结构.json"}],"author":{"name":"ZestJourney","slug":"blog-author","avatar":"https://zjpicture.oss-cn-beijing.aliyuncs.com/img/20210822091020.jpg","link":"/","description":"吾好梦中读书~","socials":{"github":"","twitter":"","stackoverflow":"","wechat":"","qq":"","weibo":"","zhihu":"","csdn":"","juejin":"","customs":{"QQ":{"icon":"/svg/qq.svg","link":"https://gitee.com/zhangjie0524/picgo/raw/master/20210822092319.jpg"},"WeiXin":{"icon":"/svg/weixin.svg","link":"https://gitee.com/zhangjie0524/picgo/raw/master/20210822092515.png"},"Github":{"icon":"/svg/github.svg","link":"https://github.com/zestaken"}}}}},{"title":"第一章 数据结构及算法概念","uid":"257f7ecf1d2df627fe532c04ea19a968","slug":"专业基础/数据结构/第一章 数据结构及算法概念","date":"2020-06-28T09:25:37.000Z","updated":"2021-09-26T13:34:19.067Z","comments":true,"path":"api/articles/专业基础/数据结构/第一章 数据结构及算法概念.json","cover":[],"text":" 第一章 绪论 1.数据结构的基本概念 数据的基本概念 默认情况下，程序中处理的数据都是数据对象。 数据结构定义 数据结构 = 数据对象 + 结构 结构:数据元素之间的关系 数据结构的组成 逻辑结构：数据元素间的逻辑关系 逻辑结构的表示 表 二元组 图形 逻辑结构的分类 线性结构...","link":"","photos":[],"count_time":{"symbolsCount":"8.2k","symbolsTime":"7 mins."},"categories":[{"name":"专业基础","slug":"专业基础","count":24,"path":"api/categories/专业基础.json"},{"name":"数据结构","slug":"专业基础/数据结构","count":8,"path":"api/categories/专业基础/数据结构.json"}],"tags":[{"name":"数据结构","slug":"数据结构","count":14,"path":"api/tags/数据结构.json"}],"author":{"name":"ZestJourney","slug":"blog-author","avatar":"https://zjpicture.oss-cn-beijing.aliyuncs.com/img/20210822091020.jpg","link":"/","description":"吾好梦中读书~","socials":{"github":"","twitter":"","stackoverflow":"","wechat":"","qq":"","weibo":"","zhihu":"","csdn":"","juejin":"","customs":{"QQ":{"icon":"/svg/qq.svg","link":"https://gitee.com/zhangjie0524/picgo/raw/master/20210822092319.jpg"},"WeiXin":{"icon":"/svg/weixin.svg","link":"https://gitee.com/zhangjie0524/picgo/raw/master/20210822092515.png"},"Github":{"icon":"/svg/github.svg","link":"https://github.com/zestaken"}}}}},{"title":"Linux基础","uid":"144f0b4d9b9f80ea377106e9c6a54a45","slug":"技术笔记/Linux/Linux基础","date":"2020-06-20T03:42:45.000Z","updated":"2021-09-26T13:41:25.469Z","comments":true,"path":"api/articles/技术笔记/Linux/Linux基础.json","cover":[],"text":" Linux linux命令参考 一、操作系统简介 ubuntu阿里云镜像地址 计算机是一台机器，它按照用户的要求接收信息、存储数据、处理数据，然后再将处理结果输出（文字、图片、音频、视频等）。计算机由硬件和软件组成。 操作系统（Operating System，OS）是软件的一...","link":"","photos":[],"count_time":{"symbolsCount":"52k","symbolsTime":"47 mins."},"categories":[{"name":"技术笔记","slug":"技术笔记","count":67,"path":"api/categories/技术笔记.json"},{"name":"Linux","slug":"技术笔记/Linux","count":6,"path":"api/categories/技术笔记/Linux.json"}],"tags":[{"name":"Linux","slug":"Linux","count":6,"path":"api/tags/Linux.json"}],"author":{"name":"ZestJourney","slug":"blog-author","avatar":"https://zjpicture.oss-cn-beijing.aliyuncs.com/img/20210822091020.jpg","link":"/","description":"吾好梦中读书~","socials":{"github":"","twitter":"","stackoverflow":"","wechat":"","qq":"","weibo":"","zhihu":"","csdn":"","juejin":"","customs":{"QQ":{"icon":"/svg/qq.svg","link":"https://gitee.com/zhangjie0524/picgo/raw/master/20210822092319.jpg"},"WeiXin":{"icon":"/svg/weixin.svg","link":"https://gitee.com/zhangjie0524/picgo/raw/master/20210822092515.png"},"Github":{"icon":"/svg/github.svg","link":"https://github.com/zestaken"}}}}},{"title":"MarkdownLearn","uid":"08f95f8bb3207471e514066523b9db43","slug":"技术笔记/杂技术/MarkdownLearn","date":"2020-06-19T03:58:46.000Z","updated":"2021-09-26T13:40:06.006Z","comments":true,"path":"api/articles/技术笔记/杂技术/MarkdownLearn.json","cover":[],"text":" MarkdownLearn 一、Markdown简介 Markdown是一种可以使用普通文本编辑器编写的标记语言，通过简单的标记语法，它可以使普通文本内容具有一定的格式。 Markdown具有一系列衍生版本，用于扩展Markdown的功能（如表格、脚注、内嵌HTML等等），这些...","link":"","photos":[],"count_time":{"symbolsCount":"4.8k","symbolsTime":"4 mins."},"categories":[{"name":"技术笔记","slug":"技术笔记","count":67,"path":"api/categories/技术笔记.json"},{"name":"杂技术","slug":"技术笔记/杂技术","count":8,"path":"api/categories/技术笔记/杂技术.json"}],"tags":[{"name":"杂技术","slug":"杂技术","count":5,"path":"api/tags/杂技术.json"},{"name":"Markdown","slug":"Markdown","count":1,"path":"api/tags/Markdown.json"}],"author":{"name":"ZestJourney","slug":"blog-author","avatar":"https://zjpicture.oss-cn-beijing.aliyuncs.com/img/20210822091020.jpg","link":"/","description":"吾好梦中读书~","socials":{"github":"","twitter":"","stackoverflow":"","wechat":"","qq":"","weibo":"","zhihu":"","csdn":"","juejin":"","customs":{"QQ":{"icon":"/svg/qq.svg","link":"https://gitee.com/zhangjie0524/picgo/raw/master/20210822092319.jpg"},"WeiXin":{"icon":"/svg/weixin.svg","link":"https://gitee.com/zhangjie0524/picgo/raw/master/20210822092515.png"},"Github":{"icon":"/svg/github.svg","link":"https://github.com/zestaken"}}}}}]}