{"name":"Redis","slug":"Redis","count":1,"postlist":[{"title":"Redis","uid":"a978a5e93d8e6628e9f4ee713be55be8","slug":"技术笔记/Web后端/Redis","date":"2021-01-30T03:09:31.000Z","updated":"2021-09-26T13:39:41.494Z","comments":true,"path":"api/articles/技术笔记/Web后端/Redis.json","keywords":null,"cover":null,"text":"Redis概念 redis是一款高性能的NOSQL系列的非关系型数据库。 Redis（Remote Dictionary Server )，即远程字典服务，是一个开源的使用ANSI C语言编写、支持网络、可基于内存亦可持久化的日志型、Key-Value数据库，并提供多种语言的AP...","link":"","photos":[],"count_time":{"symbolsCount":"4.4k","symbolsTime":"4 mins."},"categories":[{"name":"技术笔记","slug":"技术笔记","count":52,"path":"api/categories/技术笔记.json"},{"name":"Web后端","slug":"技术笔记/Web后端","count":24,"path":"api/categories/技术笔记/Web后端.json"}],"tags":[{"name":"后端","slug":"后端","count":21,"path":"api/tags/后端.json"},{"name":"Redis","slug":"Redis","count":1,"path":"api/tags/Redis.json"}],"author":{"name":"ZestJourney","slug":"blog-author","avatar":"https://zjpicture.oss-cn-beijing.aliyuncs.com/img/20210822091020.jpg","link":"/","description":"吾好梦中读书~","socials":{"github":"","twitter":"","stackoverflow":"","wechat":"","qq":"","weibo":"","zhihu":"","csdn":"","juejin":"","customs":{"QQ":{"icon":"/svg/qq.svg","link":"https://gitee.com/zhangjie0524/picgo/raw/master/20210822092319.jpg"},"WeiXin":{"icon":"/svg/weixin.svg","link":"https://gitee.com/zhangjie0524/picgo/raw/master/20210822092515.png"},"Github":{"icon":"/svg/github.svg","link":"https://github.com/zestaken"}}}}}]}