{"title":"计算机基本快捷键","uid":"81233226b7bc02864b132d2645d6b727","slug":"技术笔记/杂技术/计算机基本快捷键","date":"2020-09-02T03:19:05.000Z","updated":"2021-09-26T13:40:35.318Z","comments":true,"path":"api/articles/技术笔记/杂技术/计算机基本快捷键.json","keywords":null,"cover":null,"content":"<h1 id=\"windows系统快捷键\"><a class=\"markdownIt-Anchor\" href=\"#windows系统快捷键\"></a> Windows系统快捷键</h1>\n<ul>\n<li>带Windows键</li>\n</ul>\n<table>\n<thead>\n<tr>\n<th>快捷键</th>\n<th>作用</th>\n<th>说明</th>\n</tr>\n</thead>\n<tbody>\n<tr>\n<td>win</td>\n<td>开始菜单</td>\n<td>按Esc或者再按下win可以退出开始菜单</td>\n</tr>\n<tr>\n<td>win + S</td>\n<td>调出搜索</td>\n<td></td>\n</tr>\n<tr>\n<td>win + E</td>\n<td>调出文件资源管理器</td>\n<td>可反复使用打开多个文件资源管理器窗口</td>\n</tr>\n<tr>\n<td>win + R</td>\n<td>调出运行命令</td>\n<td>常用来打开注册表</td>\n</tr>\n<tr>\n<td>win +T</td>\n<td>调出底部任务栏，并在其中切换</td>\n<td>多次按下win + T可在底部任务栏中顺序切换，按下Esc可以退出选择</td>\n</tr>\n<tr>\n<td>win +数字</td>\n<td>可在底部任务栏中快速切换，排在第几，就对应第几个数字</td>\n<td>再次按下可以最小化窗口</td>\n</tr>\n<tr>\n<td>win + U</td>\n<td>可以直接打开Windows的系统设置窗口</td>\n<td></td>\n</tr>\n<tr>\n<td>win + A</td>\n<td>打开通知中心</td>\n<td>按Esc可以退出</td>\n</tr>\n<tr>\n<td>win + D</td>\n<td>最小化所有窗口</td>\n<td>再次按下可以恢复</td>\n</tr>\n<tr>\n<td>win + G</td>\n<td>启动Xbox屏幕录制</td>\n<td>不会直接录制，而是先进入Xbox的操作界面</td>\n</tr>\n<tr>\n<td>win + Alt + R</td>\n<td>等待一下下后直接开始屏幕录制</td>\n<td>再次按下，则停止录制并保存到C:\\Users\\12246\\Videos\\Captures，可选择录制声音</td>\n</tr>\n<tr>\n<td>win + K</td>\n<td>打开无线连接设备</td>\n<td>如蓝牙</td>\n</tr>\n<tr>\n<td>win + L</td>\n<td>锁定计算机</td>\n<td>进入需要密码进入的状态</td>\n</tr>\n<tr>\n<td>win + x</td>\n<td>调出系统快捷菜单</td>\n<td></td>\n</tr>\n<tr>\n<td>win + 空格</td>\n<td>在输入法之间切换</td>\n<td></td>\n</tr>\n<tr>\n<td>win + 上方向键</td>\n<td>总体上可使当前窗口向上移动分屏，连按几次后进入最大化窗口</td>\n<td></td>\n</tr>\n<tr>\n<td>win + 下方向键</td>\n<td>总体上可使当前窗口向下移动分屏，连按几次后进入最小化窗口</td>\n<td></td>\n</tr>\n<tr>\n<td>win + 左/右方向键</td>\n<td>使当前窗口左右分屏或者移动</td>\n<td>到达边界后弹向相反的另一方</td>\n</tr>\n<tr>\n<td>win + Tab</td>\n<td>进入时间轴任务窗口模式</td>\n<td>再按一次或者Esc可以回到正常窗口</td>\n</tr>\n<tr>\n<td>win + Alt + D</td>\n<td>打开日历</td>\n<td></td>\n</tr>\n</tbody>\n</table>\n<ul>\n<li>其它</li>\n</ul>\n<table>\n<thead>\n<tr>\n<th>快捷键</th>\n<th>作用</th>\n<th>说明</th>\n</tr>\n</thead>\n<tbody>\n<tr>\n<td>Ctrl键按住</td>\n<td>与鼠标左键配合可以选择不连续的多个文件</td>\n<td></td>\n</tr>\n<tr>\n<td>shift键按住</td>\n<td>与鼠标左键配合可以选择连续的多个文件</td>\n<td></td>\n</tr>\n<tr>\n<td>Ctrl + A</td>\n<td>全选</td>\n<td></td>\n</tr>\n<tr>\n<td>Ctrl + C</td>\n<td>复制选择的项目</td>\n<td></td>\n</tr>\n<tr>\n<td>Ctrl + X</td>\n<td>剪切选择的项目</td>\n<td></td>\n</tr>\n<tr>\n<td>Ctrl + V</td>\n<td>粘贴被复制或者剪切的项目</td>\n<td></td>\n</tr>\n<tr>\n<td>Ctrl + Z</td>\n<td>撤销刚才的操作</td>\n<td></td>\n</tr>\n<tr>\n<td>ctrl + Y</td>\n<td>重新执行刚才的操作</td>\n<td>差不多是反撤销，可以理解为撤销被撤销的操作</td>\n</tr>\n<tr>\n<td>Ctrl + F</td>\n<td>查找当前页面的指定字符</td>\n<td></td>\n</tr>\n<tr>\n<td>Alt + tab</td>\n<td>显示当前所有窗口</td>\n<td>按住Alt再按tab可以顺序选中不同的窗口,松手后进入选中的页面</td>\n</tr>\n<tr>\n<td>F11</td>\n<td>进入全屏</td>\n<td>比普通方法进入全屏更强，可以连上边栏的显示也直接关掉，再次按下可关闭全屏</td>\n</tr>\n</tbody>\n</table>\n<h1 id=\"vscode快捷键\"><a class=\"markdownIt-Anchor\" href=\"#vscode快捷键\"></a> vscode快捷键</h1>\n<ul>\n<li>总控制</li>\n</ul>\n<table>\n<thead>\n<tr>\n<th>快捷键</th>\n<th>作用</th>\n<th>说明</th>\n</tr>\n</thead>\n<tbody>\n<tr>\n<td>CTRL + Shift + P、F1</td>\n<td>打开顶部命令控制</td>\n<td>ctrl + shift + P 会有失灵的时候</td>\n</tr>\n<tr>\n<td>Ctrl + P</td>\n<td>打开快捷控制窗口</td>\n<td>这个窗口可以快速查找一些当前文件夹下的文件</td>\n</tr>\n<tr>\n<td>Ctrl + shift + N</td>\n<td>创建一个全新的vscode窗口</td>\n<td></td>\n</tr>\n<tr>\n<td>Ctrl + shift + W</td>\n<td>关闭当前窗口</td>\n<td></td>\n</tr>\n<tr>\n<td>Ctrl + ,</td>\n<td>打开设置（settings）窗口</td>\n<td></td>\n</tr>\n<tr>\n<td>Ctrl + K + Ctrl + S</td>\n<td>打开设置快捷键的窗口</td>\n<td></td>\n</tr>\n</tbody>\n</table>\n<ul>\n<li>文本编辑</li>\n</ul>\n<table>\n<thead>\n<tr>\n<th>快捷键</th>\n<th>作用</th>\n<th>说明</th>\n</tr>\n</thead>\n<tbody>\n<tr>\n<td>Ctrl + X</td>\n<td>剪切选中部分</td>\n<td>与vim插件有冲突，不能使用</td>\n</tr>\n<tr>\n<td>Ctrl + C</td>\n<td>复制选中的部分</td>\n<td>与vim插件冲突，不能使用</td>\n</tr>\n<tr>\n<td>Alt + 上下方向键</td>\n<td>向上或者向下一行一行的移动当前行</td>\n<td></td>\n</tr>\n<tr>\n<td>shift + Alt + 上下方向键</td>\n<td>向上或者向下复制当前行的内容</td>\n<td></td>\n</tr>\n<tr>\n<td>ctrl + shift + K</td>\n<td>删除当前行</td>\n<td></td>\n</tr>\n<tr>\n<td>Ctrl + enter</td>\n<td>在当前行下面插入一行</td>\n<td></td>\n</tr>\n<tr>\n<td>Ctrl + shift +enter</td>\n<td>在当前行上面插入一行</td>\n<td></td>\n</tr>\n<tr>\n<td>Ctrl + 上下方向键</td>\n<td>向上下移动页面一行行地移动页面</td>\n<td></td>\n</tr>\n</tbody>\n</table>\n<ul>\n<li>界面控制</li>\n</ul>\n<table>\n<thead>\n<tr>\n<th>快捷键</th>\n<th>作用</th>\n<th>说明</th>\n</tr>\n</thead>\n<tbody>\n<tr>\n<td>Ctrl + F4，Ctrl + W</td>\n<td>关闭当前编辑页</td>\n<td>Ctrl + w不知为何用不了</td>\n</tr>\n<tr>\n<td>ctrl +|拆分当前编辑页面（向右）</td>\n<td></td>\n<td></td>\n</tr>\n<tr>\n<td>ctrl + 数字</td>\n<td>进入第几个拆分页面</td>\n<td></td>\n</tr>\n<tr>\n<td>ctrl + K +方向键</td>\n<td>调整拆分页面的排列方式</td>\n<td></td>\n</tr>\n<tr>\n<td>Ctrl + shift + `</td>\n<td>打开内置的终端</td>\n<td></td>\n</tr>\n</tbody>\n</table>\n<ul>\n<li>文件控制</li>\n</ul>\n<table>\n<thead>\n<tr>\n<th>快捷键</th>\n<th>作用</th>\n<th>说明</th>\n</tr>\n</thead>\n<tbody>\n<tr>\n<td>Ctrl + N</td>\n<td>创建新的编辑文档</td>\n<td>要在特定的位置按下才有用</td>\n</tr>\n<tr>\n<td>Ctrl + O</td>\n<td>需要在文件选项下按才会有打开文件资源管理器的效果</td>\n<td></td>\n</tr>\n<tr>\n<td>Ctrl + F4</td>\n<td>关闭当前的标签页</td>\n<td></td>\n</tr>\n<tr>\n<td>Ctrl + tab</td>\n<td>在标签页之间切换</td>\n<td></td>\n</tr>\n<tr>\n<td>ctrl + +/-</td>\n<td>控制窗口和字体的大小</td>\n<td></td>\n</tr>\n<tr>\n<td>Ctrl + B</td>\n<td>打开侧栏</td>\n<td></td>\n</tr>\n<tr>\n<td>Ctrl +shift+ E</td>\n<td>打开侧边栏文件管理</td>\n<td></td>\n</tr>\n<tr>\n<td>Ctrl + shift + F</td>\n<td>打开侧边栏查找</td>\n<td></td>\n</tr>\n<tr>\n<td>Ctrl + shift + G</td>\n<td>打开侧边栏版本管理</td>\n<td></td>\n</tr>\n<tr>\n<td>Ctrl + shift + D</td>\n<td>打开侧边栏debug</td>\n<td></td>\n</tr>\n<tr>\n<td>Ctrl + shift + X</td>\n<td>打开侧边栏扩展</td>\n<td></td>\n</tr>\n<tr>\n<td>Ctrl + shift + V</td>\n<td>打开Markdown预览</td>\n<td></td>\n</tr>\n</tbody>\n</table>\n<ul>\n<li>调试</li>\n</ul>\n<table>\n<thead>\n<tr>\n<th>快捷键</th>\n<th>作用</th>\n<th>说明</th>\n</tr>\n</thead>\n<tbody>\n<tr>\n<td>F9</td>\n<td>设置断点</td>\n<td></td>\n</tr>\n<tr>\n<td>F5</td>\n<td>开始调试</td>\n<td></td>\n</tr>\n<tr>\n<td>Shift +F5</td>\n<td>停止调试</td>\n<td></td>\n</tr>\n</tbody>\n</table>\n","text":" Windows系统快捷键 带Windows键 快捷键 作用 说明 win 开始菜单 按Esc或者再按下win可以退出开始菜单 win + S 调出搜索 win + E 调出文件资源管理器 可反复使用打开多个文件资源管理器窗口 win + R 调出运行命令 常用来打开注册表 wi...","link":"","photos":[],"count_time":{"symbolsCount":"2.3k","symbolsTime":"2 mins."},"categories":[{"name":"技术笔记","slug":"技术笔记","count":52,"path":"api/categories/技术笔记.json"},{"name":"杂技术","slug":"技术笔记/杂技术","count":5,"path":"api/categories/技术笔记/杂技术.json"}],"tags":[{"name":"杂技术","slug":"杂技术","count":5,"path":"api/tags/杂技术.json"}],"toc":"<ol class=\"toc\"><li class=\"toc-item toc-level-1\"><a class=\"toc-link\" href=\"#windows%E7%B3%BB%E7%BB%9F%E5%BF%AB%E6%8D%B7%E9%94%AE\"><span class=\"toc-text\"> Windows系统快捷键</span></a></li><li class=\"toc-item toc-level-1\"><a class=\"toc-link\" href=\"#vscode%E5%BF%AB%E6%8D%B7%E9%94%AE\"><span class=\"toc-text\"> vscode快捷键</span></a></li></ol>","author":{"name":"ZestJourney","slug":"blog-author","avatar":"https://zjpicture.oss-cn-beijing.aliyuncs.com/img/20210822091020.jpg","link":"/","description":"吾好梦中读书~","socials":{"github":"","twitter":"","stackoverflow":"","wechat":"","qq":"","weibo":"","zhihu":"","csdn":"","juejin":"","customs":{"QQ":{"icon":"/svg/qq.svg","link":"https://gitee.com/zhangjie0524/picgo/raw/master/20210822092319.jpg"},"WeiXin":{"icon":"/svg/weixin.svg","link":"https://gitee.com/zhangjie0524/picgo/raw/master/20210822092515.png"},"Github":{"icon":"/svg/github.svg","link":"https://github.com/zestaken"}}}},"mapped":true,"prev_post":{"title":"Python","uid":"7d84a4176eacfd91fe4b92da8af8cc6a","slug":"技术笔记/Python/Python","date":"2020-09-05T12:45:19.000Z","updated":"2021-09-26T13:42:19.458Z","comments":true,"path":"api/articles/技术笔记/Python/Python.json","keywords":null,"cover":null,"text":" python概述 Python是一门解释性语言，无需编译和链接。 Python解释器是可以交互的，因此Python甚至可以用作桌面计算器。 Python是可扩展的，可以为Python的解释器添加内置函数和模块。 本文学习的是Python3. 解释器 trackback:程序无法...","link":"","photos":[],"count_time":{"symbolsCount":"30k","symbolsTime":"27 mins."},"categories":[{"name":"技术笔记","slug":"技术笔记","count":52,"path":"api/categories/技术笔记.json"},{"name":"Python","slug":"技术笔记/Python","count":2,"path":"api/categories/技术笔记/Python.json"}],"tags":[{"name":"Python","slug":"Python","count":3,"path":"api/tags/Python.json"}],"author":{"name":"ZestJourney","slug":"blog-author","avatar":"https://zjpicture.oss-cn-beijing.aliyuncs.com/img/20210822091020.jpg","link":"/","description":"吾好梦中读书~","socials":{"github":"","twitter":"","stackoverflow":"","wechat":"","qq":"","weibo":"","zhihu":"","csdn":"","juejin":"","customs":{"QQ":{"icon":"/svg/qq.svg","link":"https://gitee.com/zhangjie0524/picgo/raw/master/20210822092319.jpg"},"WeiXin":{"icon":"/svg/weixin.svg","link":"https://gitee.com/zhangjie0524/picgo/raw/master/20210822092515.png"},"Github":{"icon":"/svg/github.svg","link":"https://github.com/zestaken"}}}}},"next_post":{"title":"第七章 图","uid":"944ed7c2eb91eed305ac927a8ab2efa7","slug":"专业基础/数据结构/第七章 图","date":"2020-08-14T16:45:37.000Z","updated":"2021-09-26T13:34:19.067Z","comments":true,"path":"api/articles/专业基础/数据结构/第七章 图.json","keywords":null,"cover":[],"text":" 图 由于考试压力。。。还有待完善。。。 图的定义 图由顶点集合和边集合产生 有向图和无向图 有向图的边带有箭头，而无向图的边没有箭头。 无向边用()表示，而有向边用&lt;&gt;表示。 图的基本术语 端点和邻接点 一条边的两头的顶点为端点，这两个端点互为邻接点。 顶点的度、入...","link":"","photos":[],"count_time":{"symbolsCount":"6.5k","symbolsTime":"6 mins."},"categories":[{"name":"专业基础","slug":"专业基础","count":17,"path":"api/categories/专业基础.json"},{"name":"数据结构","slug":"专业基础/数据结构","count":8,"path":"api/categories/专业基础/数据结构.json"}],"tags":[{"name":"数据结构","slug":"数据结构","count":14,"path":"api/tags/数据结构.json"}],"author":{"name":"ZestJourney","slug":"blog-author","avatar":"https://zjpicture.oss-cn-beijing.aliyuncs.com/img/20210822091020.jpg","link":"/","description":"吾好梦中读书~","socials":{"github":"","twitter":"","stackoverflow":"","wechat":"","qq":"","weibo":"","zhihu":"","csdn":"","juejin":"","customs":{"QQ":{"icon":"/svg/qq.svg","link":"https://gitee.com/zhangjie0524/picgo/raw/master/20210822092319.jpg"},"WeiXin":{"icon":"/svg/weixin.svg","link":"https://gitee.com/zhangjie0524/picgo/raw/master/20210822092515.png"},"Github":{"icon":"/svg/github.svg","link":"https://github.com/zestaken"}}}}}}